chassispy/UGVConfigMsg.py
chassispy/__init__.py
chassispy/chassispy.py
chassispy-0.5.0.dist-info/LICENSE.txt
chassispy-0.5.0.dist-info/METADATA
chassispy-0.5.0.dist-info/WHEEL
chassispy-0.5.0.dist-info/top_level.txt
chassispy-0.5.0.dist-info/RECORD
