Metadata-Version: 2.1
Name: chassispy
Version: 0.5.0
Summary: A small example package
Home-page: https://github.com/88588421/agilex_chassis
Author: tang xi
Author-email: tang___xi@163.com
License: UNKNOWN
Project-URL: Bug Tracker, https://github.com/88588421/agilex_chassis/issues
Platform: UNKNOWN
Classifier: Programming Language :: Python :: 3.6
Classifier: Programming Language :: Python :: 3.7
Classifier: Programming Language :: Python :: 3.8
Classifier: Programming Language :: Python :: 3.9
Classifier: License :: OSI Approved :: MIT License
Requires-Python: >=3.6
License-File: LICENSE.txt
Requires-Dist: python-can (>=3.3.4)
